sendysms/__init__.py
sendysms-0.3.dist-info/METADATA
sendysms-0.3.dist-info/WHEEL
sendysms-0.3.dist-info/top_level.txt
sendysms-0.3.dist-info/RECORD
